{
  "Id": "spec-diagram-designer",
  "Payload": {
    "Case": "SpecNode",
    "Fields": {
      "Item": {
        "Title": "Diagramm-Designer",
        "Intent": "Eine Zeichenfl\u00E4che, viele Projektionen: Klassen, Use Case, Sequenz, Architektur, Topologie, Grid \u2014 alle Cube-gefiltert",
        "Criteria": [
          {
            "Given": "ein aktiver Cube-Filter oder Fokus",
            "When": "zwischen Designer-Sichten gewechselt wird",
            "Then": "zeigt jede Sicht dieselbe gefilterte Teilmenge in ihrer Projektion"
          },
          {
            "Given": "eine Grid-Kachel",
            "When": "sie angeklickt wird",
            "Then": "wird in die Topologie des Knotens gedrillt (Fokus an)"
          }
        ]
      }
    }
  },
  "Convergence": "Aligned"
}